[
  {
    "data": "הגבעה הצהובה",
    "date": "12.03.2026",
    "time": "09:38:05",
    "alertDate": "2026-03-12T09:38:00",
    "category": 13,
    "category_desc": "האירוע הסתיים",
    "matrix_id": 10,
    "rid": 465137,
    "title": "האירוע הסתיים"
  },
  {
    "data": "הגבעה הצהובה",
    "date": "12.03.2026",
    "time": "09:25:56",
    "alertDate": "2026-03-12T09:26:00",
    "category": 1,
    "category_desc": "ירי רקטות וטילים",
    "matrix_id": 1,
    "rid": 464572,
    "title": "ירי רקטות וטילים"
  },
  {
    "data": "הגבעה הצהובה",
    "date": "12.03.2026",
    "time": "09:22:15",
    "alertDate": "2026-03-12T09:22:00",
    "category": 14,
    "category_desc": "בדקות הקרובות צפויות להתקבל התרעות באזורך",
    "matrix_id": 10,
    "rid": 464065,
    "title": "בדקות הקרובות צפויות להתקבל התרעות באזורך"
  },
  {
    "data": "הגבעה הצהובה",
    "date": "12.03.2026",
    "time": "04:25:09",
    "alertDate": "2026-03-12T04:25:00",
    "category": 13,
    "category_desc": "האירוע הסתיים",
    "matrix_id": 10,
    "rid": 461640,
    "title": "האירוע הסתיים"
  },
  {
    "data": "הגבעה הצהובה",
    "date": "12.03.2026",
    "time": "04:07:30",
    "alertDate": "2026-03-12T04:08:00",
    "category": 14,
    "category_desc": "בדקות הקרובות צפויות להתקבל התרעות באזורך",
    "matrix_id": 10,
    "rid": 459925,
    "title": "בדקות הקרובות צפויות להתקבל התרעות באזורך"
  },
  {
    "data": "הגבעה הצהובה",
    "date": "12.03.2026",
    "time": "00:46:51",
    "alertDate": "2026-03-12T00:47:00",
    "category": 13,
    "category_desc": "האירוע הסתיים",
    "matrix_id": 10,
    "rid": 459094,
    "title": "האירוע הסתיים"
  },
  {
    "data": "הגבעה הצהובה",
    "date": "12.03.2026",
    "time": "00:34:32",
    "alertDate": "2026-03-12T00:35:00",
    "category": 1,
    "category_desc": "ירי רקטות וטילים",
    "matrix_id": 1,
    "rid": 458554,
    "title": "ירי רקטות וטילים"
  },
  {
    "data": "הגבעה הצהובה",
    "date": "12.03.2026",
    "time": "00:30:02",
    "alertDate": "2026-03-12T00:30:00",
    "category": 14,
    "category_desc": "בדקות הקרובות צפויות להתקבל התרעות באזורך",
    "matrix_id": 10,
    "rid": 457778,
    "title": "בדקות הקרובות צפויות להתקבל התרעות באזורך"
  },
  {
    "data": "הגבעה הצהובה",
    "date": "11.03.2026",
    "time": "19:57:45",
    "alertDate": "2026-03-11T19:58:00",
    "category": 13,
    "category_desc": "האירוע הסתיים",
    "matrix_id": 10,
    "rid": 453481,
    "title": "האירוע הסתיים"
  },
  {
    "data": "הגבעה הצהובה",
    "date": "11.03.2026",
    "time": "19:46:12",
    "alertDate": "2026-03-11T19:46:00",
    "category": 1,
    "category_desc": "ירי רקטות וטילים",
    "matrix_id": 1,
    "rid": 452987,
    "title": "ירי רקטות וטילים"
  },
  {
    "data": "הגבעה הצהובה",
    "date": "11.03.2026",
    "time": "19:38:48",
    "alertDate": "2026-03-11T19:39:00",
    "category": 14,
    "category_desc": "בדקות הקרובות צפויות להתקבל התרעות באזורך",
    "matrix_id": 10,
    "rid": 452358,
    "title": "בדקות הקרובות צפויות להתקבל התרעות באזורך"
  },
  {
    "data": "הגבעה הצהובה",
    "date": "11.03.2026",
    "time": "14:05:13",
    "alertDate": "2026-03-11T14:05:00",
    "category": 13,
    "category_desc": "האירוע הסתיים",
    "matrix_id": 10,
    "rid": 451672,
    "title": "האירוע הסתיים"
  },
  {
    "data": "הגבעה הצהובה",
    "date": "11.03.2026",
    "time": "13:41:44",
    "alertDate": "2026-03-11T13:42:00",
    "category": 14,
    "category_desc": "בדקות הקרובות צפויות להתקבל התרעות באזורך",
    "matrix_id": 10,
    "rid": 449520,
    "title": "בדקות הקרובות צפויות להתקבל התרעות באזורך"
  },
  {
    "data": "הגבעה הצהובה",
    "date": "11.03.2026",
    "time": "04:50:04",
    "alertDate": "2026-03-11T04:50:00",
    "category": 13,
    "category_desc": "האירוע הסתיים",
    "matrix_id": 10,
    "rid": 448810,
    "title": "האירוע הסתיים"
  },
  {
    "data": "הגבעה הצהובה",
    "date": "11.03.2026",
    "time": "04:32:02",
    "alertDate": "2026-03-11T04:32:00",
    "category": 14,
    "category_desc": "בדקות הקרובות צפויות להתקבל התרעות באזורך",
    "matrix_id": 10,
    "rid": 447981,
    "title": "בדקות הקרובות צפויות להתקבל התרעות באזורך"
  },
  {
    "data": "הגבעה הצהובה",
    "date": "11.03.2026",
    "time": "04:00:38",
    "alertDate": "2026-03-11T04:01:00",
    "category": 13,
    "category_desc": "האירוע הסתיים",
    "matrix_id": 10,
    "rid": 447309,
    "title": "האירוע הסתיים"
  },
  {
    "data": "הגבעה הצהובה",
    "date": "11.03.2026",
    "time": "03:41:09",
    "alertDate": "2026-03-11T03:41:00",
    "category": 14,
    "category_desc": "בדקות הקרובות צפויות להתקבל התרעות באזורך",
    "matrix_id": 10,
    "rid": 446221,
    "title": "בדקות הקרובות צפויות להתקבל התרעות באזורך"
  },
  {
    "data": "הגבעה הצהובה",
    "date": "11.03.2026",
    "time": "01:21:36",
    "alertDate": "2026-03-11T01:22:00",
    "category": 13,
    "category_desc": "האירוע הסתיים",
    "matrix_id": 10,
    "rid": 444994,
    "title": "האירוע הסתיים"
  },
  {
    "data": "הגבעה הצהובה",
    "date": "11.03.2026",
    "time": "01:03:35",
    "alertDate": "2026-03-11T01:04:00",
    "category": 14,
    "category_desc": "בדקות הקרובות צפויות להתקבל התרעות באזורך",
    "matrix_id": 10,
    "rid": 443325,
    "title": "בדקות הקרובות צפויות להתקבל התרעות באזורך"
  },
  {
    "data": "הגבעה הצהובה",
    "date": "11.03.2026",
    "time": "00:55:18",
    "alertDate": "2026-03-11T00:55:00",
    "category": 1,
    "category_desc": "ירי רקטות וטילים",
    "matrix_id": 1,
    "rid": 443034,
    "title": "ירי רקטות וטילים"
  },
  {
    "data": "הגבעה הצהובה",
    "date": "11.03.2026",
    "time": "00:49:29",
    "alertDate": "2026-03-11T00:49:00",
    "category": 14,
    "category_desc": "בדקות הקרובות צפויות להתקבל התרעות באזורך",
    "matrix_id": 10,
    "rid": 442499,
    "title": "בדקות הקרובות צפויות להתקבל התרעות באזורך"
  },
  {
    "data": "הגבעה הצהובה",
    "date": "10.03.2026",
    "time": "23:48:14",
    "alertDate": "2026-03-10T23:48:00",
    "category": 13,
    "category_desc": "האירוע הסתיים",
    "matrix_id": 10,
    "rid": 441819,
    "title": "האירוע הסתיים"
  },
  {
    "data": "הגבעה הצהובה",
    "date": "10.03.2026",
    "time": "23:32:02",
    "alertDate": "2026-03-10T23:32:00",
    "category": 14,
    "category_desc": "בדקות הקרובות צפויות להתקבל התרעות באזורך",
    "matrix_id": 10,
    "rid": 440787,
    "title": "בדקות הקרובות צפויות להתקבל התרעות באזורך"
  },
  {
    "data": "הגבעה הצהובה",
    "date": "10.03.2026",
    "time": "20:00:09",
    "alertDate": "2026-03-10T20:00:00",
    "category": 13,
    "category_desc": "האירוע הסתיים",
    "matrix_id": 10,
    "rid": 440082,
    "title": "האירוע הסתיים"
  },
  {
    "data": "הגבעה הצהובה",
    "date": "10.03.2026",
    "time": "19:43:25",
    "alertDate": "2026-03-10T19:43:00",
    "category": 14,
    "category_desc": "בדקות הקרובות צפויות להתקבל התרעות באזורך",
    "matrix_id": 10,
    "rid": 439133,
    "title": "בדקות הקרובות צפויות להתקבל התרעות באזורך"
  },
  {
    "data": "הגבעה הצהובה",
    "date": "10.03.2026",
    "time": "17:25:52",
    "alertDate": "2026-03-10T17:26:00",
    "category": 13,
    "category_desc": "האירוע הסתיים",
    "matrix_id": 10,
    "rid": 438373,
    "title": "האירוע הסתיים"
  },
  {
    "data": "הגבעה הצהובה",
    "date": "10.03.2026",
    "time": "17:12:28",
    "alertDate": "2026-03-10T17:12:00",
    "category": 1,
    "category_desc": "ירי רקטות וטילים",
    "matrix_id": 1,
    "rid": 438040,
    "title": "ירי רקטות וטילים"
  },
  {
    "data": "הגבעה הצהובה",
    "date": "10.03.2026",
    "time": "17:07:59",
    "alertDate": "2026-03-10T17:08:00",
    "category": 14,
    "category_desc": "בדקות הקרובות צפויות להתקבל התרעות באזורך",
    "matrix_id": 10,
    "rid": 437452,
    "title": "בדקות הקרובות צפויות להתקבל התרעות באזורך"
  },
  {
    "data": "הגבעה הצהובה",
    "date": "10.03.2026",
    "time": "14:54:34",
    "alertDate": "2026-03-10T14:55:00",
    "category": 13,
    "category_desc": "האירוע הסתיים",
    "matrix_id": 10,
    "rid": 436189,
    "title": "האירוע הסתיים"
  },
  {
    "data": "הגבעה הצהובה",
    "date": "10.03.2026",
    "time": "14:42:17",
    "alertDate": "2026-03-10T14:42:00",
    "category": 14,
    "category_desc": "בדקות הקרובות צפויות להתקבל התרעות באזורך",
    "matrix_id": 10,
    "rid": 435077,
    "title": "בדקות הקרובות צפויות להתקבל התרעות באזורך"
  },
  {
    "data": "הגבעה הצהובה",
    "date": "10.03.2026",
    "time": "14:21:11",
    "alertDate": "2026-03-10T14:21:00",
    "category": 14,
    "category_desc": "בדקות הקרובות צפויות להתקבל התרעות באזורך",
    "matrix_id": 10,
    "rid": 433328,
    "title": "בדקות הקרובות צפויות להתקבל התרעות באזורך"
  },
  {
    "data": "הגבעה הצהובה",
    "date": "10.03.2026",
    "time": "10:11:17",
    "alertDate": "2026-03-10T10:11:00",
    "category": 13,
    "category_desc": "האירוע הסתיים",
    "matrix_id": 10,
    "rid": 431054,
    "title": "האירוע הסתיים"
  },
  {
    "data": "הגבעה הצהובה",
    "date": "10.03.2026",
    "time": "09:53:23",
    "alertDate": "2026-03-10T09:53:00",
    "category": 14,
    "category_desc": "בדקות הקרובות צפויות להתקבל התרעות באזורך",
    "matrix_id": 10,
    "rid": 429893,
    "title": "בדקות הקרובות צפויות להתקבל התרעות באזורך"
  },
  {
    "data": "הגבעה הצהובה",
    "date": "09.03.2026",
    "time": "21:51:22",
    "alertDate": "2026-03-09T21:51:00",
    "category": 13,
    "category_desc": "האירוע הסתיים",
    "matrix_id": 10,
    "rid": 427575,
    "title": "האירוע הסתיים"
  },
  {
    "data": "הגבעה הצהובה",
    "date": "09.03.2026",
    "time": "21:34:51",
    "alertDate": "2026-03-09T21:35:00",
    "category": 14,
    "category_desc": "בדקות הקרובות צפויות להתקבל התרעות באזורך",
    "matrix_id": 10,
    "rid": 426739,
    "title": "בדקות הקרובות צפויות להתקבל התרעות באזורך"
  },
  {
    "data": "הגבעה הצהובה",
    "date": "09.03.2026",
    "time": "16:46:14",
    "alertDate": "2026-03-09T16:46:00",
    "category": 13,
    "category_desc": "האירוע הסתיים",
    "matrix_id": 10,
    "rid": 424075,
    "title": "האירוע הסתיים"
  },
  {
    "data": "הגבעה הצהובה",
    "date": "09.03.2026",
    "time": "16:30:47",
    "alertDate": "2026-03-09T16:31:00",
    "category": 14,
    "category_desc": "בדקות הקרובות צפויות להתקבל התרעות באזורך",
    "matrix_id": 10,
    "rid": 423054,
    "title": "בדקות הקרובות צפויות להתקבל התרעות באזורך"
  },
  {
    "data": "הגבעה הצהובה",
    "date": "09.03.2026",
    "time": "11:28:22",
    "alertDate": "2026-03-09T11:28:00",
    "category": 13,
    "category_desc": "האירוע הסתיים",
    "matrix_id": 10,
    "rid": 422120,
    "title": "האירוע הסתיים"
  },
  {
    "data": "הגבעה הצהובה",
    "date": "09.03.2026",
    "time": "11:07:54",
    "alertDate": "2026-03-09T11:08:00",
    "category": 14,
    "category_desc": "בדקות הקרובות צפויות להתקבל התרעות באזורך",
    "matrix_id": 10,
    "rid": 421203,
    "title": "בדקות הקרובות צפויות להתקבל התרעות באזורך"
  },
  {
    "data": "הגבעה הצהובה",
    "date": "09.03.2026",
    "time": "10:31:12",
    "alertDate": "2026-03-09T10:31:00",
    "category": 13,
    "category_desc": "האירוע הסתיים",
    "matrix_id": 10,
    "rid": 419528,
    "title": "האירוע הסתיים"
  },
  {
    "data": "הגבעה הצהובה",
    "date": "09.03.2026",
    "time": "10:20:13",
    "alertDate": "2026-03-09T10:20:00",
    "category": 1,
    "category_desc": "ירי רקטות וטילים",
    "matrix_id": 1,
    "rid": 418586,
    "title": "ירי רקטות וטילים"
  },
  {
    "data": "הגבעה הצהובה",
    "date": "09.03.2026",
    "time": "01:47:10",
    "alertDate": "2026-03-09T01:47:00",
    "category": 13,
    "category_desc": "האירוע הסתיים",
    "matrix_id": 10,
    "rid": 414087,
    "title": "האירוע הסתיים"
  },
  {
    "data": "הגבעה הצהובה",
    "date": "09.03.2026",
    "time": "01:28:42",
    "alertDate": "2026-03-09T01:29:00",
    "category": 14,
    "category_desc": "בדקות הקרובות צפויות להתקבל התרעות באזורך",
    "matrix_id": 10,
    "rid": 412044,
    "title": "בדקות הקרובות צפויות להתקבל התרעות באזורך"
  },
  {
    "data": "הגבעה הצהובה",
    "date": "09.03.2026",
    "time": "01:21:56",
    "alertDate": "2026-03-09T01:22:00",
    "category": 13,
    "category_desc": "האירוע הסתיים",
    "matrix_id": 10,
    "rid": 411408,
    "title": "האירוע הסתיים"
  },
  {
    "data": "הגבעה הצהובה",
    "date": "09.03.2026",
    "time": "01:09:18",
    "alertDate": "2026-03-09T01:09:00",
    "category": 14,
    "category_desc": "בדקות הקרובות צפויות להתקבל התרעות באזורך",
    "matrix_id": 10,
    "rid": 410075,
    "title": "בדקות הקרובות צפויות להתקבל התרעות באזורך"
  },
  {
    "data": "הגבעה הצהובה",
    "date": "08.03.2026",
    "time": "19:00:14",
    "alertDate": "2026-03-08T19:00:00",
    "category": 13,
    "category_desc": "האירוע הסתיים",
    "matrix_id": 10,
    "rid": 409044,
    "title": "האירוע הסתיים"
  },
  {
    "data": "הגבעה הצהובה",
    "date": "08.03.2026",
    "time": "18:42:59",
    "alertDate": "2026-03-08T18:43:00",
    "category": 14,
    "category_desc": "בדקות הקרובות צפויות להתקבל התרעות באזורך",
    "matrix_id": 10,
    "rid": 407776,
    "title": "בדקות הקרובות צפויות להתקבל התרעות באזורך"
  },
  {
    "data": "הגבעה הצהובה",
    "date": "08.03.2026",
    "time": "16:56:33",
    "alertDate": "2026-03-08T16:57:00",
    "category": 13,
    "category_desc": "האירוע הסתיים",
    "matrix_id": 10,
    "rid": 406744,
    "title": "האירוע הסתיים"
  },
  {
    "data": "הגבעה הצהובה",
    "date": "08.03.2026",
    "time": "16:39:17",
    "alertDate": "2026-03-08T16:39:00",
    "category": 14,
    "category_desc": "בדקות הקרובות צפויות להתקבל התרעות באזורך",
    "matrix_id": 10,
    "rid": 405710,
    "title": "בדקות הקרובות צפויות להתקבל התרעות באזורך"
  },
  {
    "data": "הגבעה הצהובה",
    "date": "08.03.2026",
    "time": "14:37:13",
    "alertDate": "2026-03-08T14:37:00",
    "category": 13,
    "category_desc": "האירוע הסתיים",
    "matrix_id": 10,
    "rid": 404811,
    "title": "האירוע הסתיים"
  },
  {
    "data": "הגבעה הצהובה",
    "date": "08.03.2026",
    "time": "14:21:15",
    "alertDate": "2026-03-08T14:21:00",
    "category": 14,
    "category_desc": "בדקות הקרובות צפויות להתקבל התרעות באזורך",
    "matrix_id": 10,
    "rid": 404035,
    "title": "בדקות הקרובות צפויות להתקבל התרעות באזורך"
  },
  {
    "data": "הגבעה הצהובה",
    "date": "08.03.2026",
    "time": "14:01:10",
    "alertDate": "2026-03-08T14:01:00",
    "category": 13,
    "category_desc": "האירוע הסתיים",
    "matrix_id": 10,
    "rid": 403179,
    "title": "האירוע הסתיים"
  },
  {
    "data": "הגבעה הצהובה",
    "date": "08.03.2026",
    "time": "13:43:09",
    "alertDate": "2026-03-08T13:43:00",
    "category": 14,
    "category_desc": "בדקות הקרובות צפויות להתקבל התרעות באזורך",
    "matrix_id": 10,
    "rid": 402349,
    "title": "בדקות הקרובות צפויות להתקבל התרעות באזורך"
  },
  {
    "data": "הגבעה הצהובה",
    "date": "08.03.2026",
    "time": "07:39:37",
    "alertDate": "2026-03-08T07:40:00",
    "category": 13,
    "category_desc": "האירוע הסתיים",
    "matrix_id": 10,
    "rid": 401392,
    "title": "האירוע הסתיים"
  },
  {
    "data": "הגבעה הצהובה",
    "date": "08.03.2026",
    "time": "07:23:33",
    "alertDate": "2026-03-08T07:24:00",
    "category": 14,
    "category_desc": "בדקות הקרובות צפויות להתקבל התרעות באזורך",
    "matrix_id": 10,
    "rid": 400437,
    "title": "בדקות הקרובות צפויות להתקבל התרעות באזורך"
  },
  {
    "data": "הגבעה הצהובה",
    "date": "08.03.2026",
    "time": "05:57:23",
    "alertDate": "2026-03-08T05:57:00",
    "category": 13,
    "category_desc": "האירוע הסתיים",
    "matrix_id": 10,
    "rid": 399520,
    "title": "האירוע הסתיים"
  },
  {
    "data": "הגבעה הצהובה",
    "date": "08.03.2026",
    "time": "05:45:53",
    "alertDate": "2026-03-08T05:46:00",
    "category": 1,
    "category_desc": "ירי רקטות וטילים",
    "matrix_id": 1,
    "rid": 399189,
    "title": "ירי רקטות וטילים"
  },
  {
    "data": "הגבעה הצהובה",
    "date": "07.03.2026",
    "time": "22:03:58",
    "alertDate": "2026-03-07T22:04:00",
    "category": 13,
    "category_desc": "האירוע הסתיים",
    "matrix_id": 10,
    "rid": 395272,
    "title": "האירוע הסתיים"
  },
  {
    "data": "הגבעה הצהובה",
    "date": "07.03.2026",
    "time": "21:46:10",
    "alertDate": "2026-03-07T21:46:00",
    "category": 14,
    "category_desc": "בדקות הקרובות צפויות להתקבל התרעות באזורך",
    "matrix_id": 10,
    "rid": 394377,
    "title": "בדקות הקרובות צפויות להתקבל התרעות באזורך"
  },
  {
    "data": "הגבעה הצהובה",
    "date": "07.03.2026",
    "time": "20:47:18",
    "alertDate": "2026-03-07T20:47:00",
    "category": 13,
    "category_desc": "האירוע הסתיים",
    "matrix_id": 10,
    "rid": 393613,
    "title": "האירוע הסתיים"
  },
  {
    "data": "הגבעה הצהובה",
    "date": "07.03.2026",
    "time": "20:29:20",
    "alertDate": "2026-03-07T20:29:00",
    "category": 14,
    "category_desc": "בדקות הקרובות צפויות להתקבל התרעות באזורך",
    "matrix_id": 10,
    "rid": 392410,
    "title": "בדקות הקרובות צפויות להתקבל התרעות באזורך"
  },
  {
    "data": "הגבעה הצהובה",
    "date": "07.03.2026",
    "time": "15:43:03",
    "alertDate": "2026-03-07T15:43:00",
    "category": 13,
    "category_desc": "האירוע הסתיים",
    "matrix_id": 10,
    "rid": 390389,
    "title": "האירוע הסתיים"
  },
  {
    "data": "הגבעה הצהובה",
    "date": "07.03.2026",
    "time": "15:25:18",
    "alertDate": "2026-03-07T15:25:00",
    "category": 14,
    "category_desc": "בדקות הקרובות צפויות להתקבל התרעות באזורך",
    "matrix_id": 10,
    "rid": 389389,
    "title": "בדקות הקרובות צפויות להתקבל התרעות באזורך"
  },
  {
    "data": "הגבעה הצהובה",
    "date": "07.03.2026",
    "time": "15:11:04",
    "alertDate": "2026-03-07T15:11:00",
    "category": 13,
    "category_desc": "האירוע הסתיים",
    "matrix_id": 10,
    "rid": 388741,
    "title": "האירוע הסתיים"
  },
  {
    "data": "הגבעה הצהובה",
    "date": "07.03.2026",
    "time": "14:49:44",
    "alertDate": "2026-03-07T14:50:00",
    "category": 14,
    "category_desc": "בדקות הקרובות צפויות להתקבל התרעות באזורך",
    "matrix_id": 10,
    "rid": 387806,
    "title": "בדקות הקרובות צפויות להתקבל התרעות באזורך"
  },
  {
    "data": "הגבעה הצהובה",
    "date": "07.03.2026",
    "time": "11:40:01",
    "alertDate": "2026-03-07T11:40:00",
    "category": 13,
    "category_desc": "האירוע הסתיים",
    "matrix_id": 10,
    "rid": 386840,
    "title": "האירוע הסתיים"
  },
  {
    "data": "הגבעה הצהובה",
    "date": "07.03.2026",
    "time": "11:28:36",
    "alertDate": "2026-03-07T11:29:00",
    "category": 1,
    "category_desc": "ירי רקטות וטילים",
    "matrix_id": 1,
    "rid": 386732,
    "title": "ירי רקטות וטילים"
  },
  {
    "data": "הגבעה הצהובה",
    "date": "07.03.2026",
    "time": "11:23:19",
    "alertDate": "2026-03-07T11:23:00",
    "category": 14,
    "category_desc": "בדקות הקרובות צפויות להתקבל התרעות באזורך",
    "matrix_id": 10,
    "rid": 386135,
    "title": "בדקות הקרובות צפויות להתקבל התרעות באזורך"
  },
  {
    "data": "הגבעה הצהובה",
    "date": "07.03.2026",
    "time": "06:40:27",
    "alertDate": "2026-03-07T06:40:00",
    "category": 13,
    "category_desc": "האירוע הסתיים",
    "matrix_id": 10,
    "rid": 385653,
    "title": "האירוע הסתיים"
  },
  {
    "data": "הגבעה הצהובה",
    "date": "07.03.2026",
    "time": "06:20:04",
    "alertDate": "2026-03-07T06:20:00",
    "category": 14,
    "category_desc": "בדקות הקרובות צפויות להתקבל התרעות באזורך",
    "matrix_id": 10,
    "rid": 384479,
    "title": "בדקות הקרובות צפויות להתקבל התרעות באזורך"
  },
  {
    "data": "הגבעה הצהובה",
    "date": "07.03.2026",
    "time": "05:38:21",
    "alertDate": "2026-03-07T05:38:00",
    "category": 13,
    "category_desc": "האירוע הסתיים",
    "matrix_id": 10,
    "rid": 383976,
    "title": "האירוע הסתיים"
  },
  {
    "data": "הגבעה הצהובה",
    "date": "07.03.2026",
    "time": "05:28:16",
    "alertDate": "2026-03-07T05:28:00",
    "category": 1,
    "category_desc": "ירי רקטות וטילים",
    "matrix_id": 1,
    "rid": 383937,
    "title": "ירי רקטות וטילים"
  },
  {
    "data": "הגבעה הצהובה",
    "date": "07.03.2026",
    "time": "05:14:35",
    "alertDate": "2026-03-07T05:15:00",
    "category": 13,
    "category_desc": "האירוע הסתיים",
    "matrix_id": 10,
    "rid": 383323,
    "title": "האירוע הסתיים"
  },
  {
    "data": "הגבעה הצהובה",
    "date": "07.03.2026",
    "time": "04:56:39",
    "alertDate": "2026-03-07T04:57:00",
    "category": 14,
    "category_desc": "בדקות הקרובות צפויות להתקבל התרעות באזורך",
    "matrix_id": 10,
    "rid": 382176,
    "title": "בדקות הקרובות צפויות להתקבל התרעות באזורך"
  },
  {
    "data": "הגבעה הצהובה",
    "date": "07.03.2026",
    "time": "00:50:04",
    "alertDate": "2026-03-07T00:50:00",
    "category": 13,
    "category_desc": "האירוע הסתיים",
    "matrix_id": 10,
    "rid": 380578,
    "title": "האירוע הסתיים"
  },
  {
    "data": "הגבעה הצהובה",
    "date": "07.03.2026",
    "time": "00:32:14",
    "alertDate": "2026-03-07T00:32:00",
    "category": 14,
    "category_desc": "בדקות הקרובות צפויות להתקבל התרעות באזורך",
    "matrix_id": 10,
    "rid": 379296,
    "title": "בדקות הקרובות צפויות להתקבל התרעות באזורך"
  },
  {
    "data": "הגבעה הצהובה",
    "date": "06.03.2026",
    "time": "22:08:29",
    "alertDate": "2026-03-06T22:08:00",
    "category": 13,
    "category_desc": "האירוע הסתיים",
    "matrix_id": 10,
    "rid": 378461,
    "title": "האירוע הסתיים"
  },
  {
    "data": "הגבעה הצהובה",
    "date": "06.03.2026",
    "time": "21:54:04",
    "alertDate": "2026-03-06T21:54:00",
    "category": 14,
    "category_desc": "בדקות הקרובות צפויות להתקבל התרעות באזורך",
    "matrix_id": 10,
    "rid": 377629,
    "title": "בדקות הקרובות צפויות להתקבל התרעות באזורך"
  },
  {
    "data": "הגבעה הצהובה",
    "date": "06.03.2026",
    "time": "20:52:55",
    "alertDate": "2026-03-06T20:53:00",
    "category": 13,
    "category_desc": "האירוע הסתיים",
    "matrix_id": 10,
    "rid": 376966,
    "title": "האירוע הסתיים"
  },
  {
    "data": "הגבעה הצהובה",
    "date": "06.03.2026",
    "time": "20:40:05",
    "alertDate": "2026-03-06T20:40:00",
    "category": 14,
    "category_desc": "בדקות הקרובות צפויות להתקבל התרעות באזורך",
    "matrix_id": 10,
    "rid": 376051,
    "title": "בדקות הקרובות צפויות להתקבל התרעות באזורך"
  },
  {
    "data": "הגבעה הצהובה",
    "date": "06.03.2026",
    "time": "19:33:49",
    "alertDate": "2026-03-06T19:34:00",
    "category": 13,
    "category_desc": "האירוע הסתיים",
    "matrix_id": 10,
    "rid": 375365,
    "title": "האירוע הסתיים"
  },
  {
    "data": "הגבעה הצהובה",
    "date": "06.03.2026",
    "time": "19:16:47",
    "alertDate": "2026-03-06T19:17:00",
    "category": 14,
    "category_desc": "בדקות הקרובות צפויות להתקבל התרעות באזורך",
    "matrix_id": 10,
    "rid": 374506,
    "title": "בדקות הקרובות צפויות להתקבל התרעות באזורך"
  },
  {
    "data": "הגבעה הצהובה",
    "date": "06.03.2026",
    "time": "10:29:21",
    "alertDate": "2026-03-06T10:29:00",
    "category": 13,
    "category_desc": "האירוע הסתיים",
    "matrix_id": 10,
    "rid": 372586,
    "title": "האירוע הסתיים"
  },
  {
    "data": "הגבעה הצהובה",
    "date": "06.03.2026",
    "time": "10:10:40",
    "alertDate": "2026-03-06T10:11:00",
    "category": 14,
    "category_desc": "בדקות הקרובות צפויות להתקבל התרעות באזורך",
    "matrix_id": 10,
    "rid": 371800,
    "title": "בדקות הקרובות צפויות להתקבל התרעות באזורך"
  },
  {
    "data": "הגבעה הצהובה",
    "date": "05.03.2026",
    "time": "23:16:12",
    "alertDate": "2026-03-05T23:16:00",
    "category": 13,
    "category_desc": "האירוע הסתיים",
    "matrix_id": 10,
    "rid": 371058,
    "title": "האירוע הסתיים"
  },
  {
    "data": "הגבעה הצהובה",
    "date": "05.03.2026",
    "time": "22:50:26",
    "alertDate": "2026-03-05T22:50:00",
    "category": 14,
    "category_desc": "בדקות הקרובות צפויות להתקבל התרעות באזורך",
    "matrix_id": 10,
    "rid": 369740,
    "title": "בדקות הקרובות צפויות להתקבל התרעות באזורך"
  },
  {
    "data": "הגבעה הצהובה",
    "date": "05.03.2026",
    "time": "22:45:54",
    "alertDate": "2026-03-05T22:46:00",
    "category": 13,
    "category_desc": "האירוע הסתיים",
    "matrix_id": 10,
    "rid": 369067,
    "title": "האירוע הסתיים"
  },
  {
    "data": "הגבעה הצהובה",
    "date": "05.03.2026",
    "time": "22:35:13",
    "alertDate": "2026-03-05T22:35:00",
    "category": 14,
    "category_desc": "בדקות הקרובות צפויות להתקבל התרעות באזורך",
    "matrix_id": 10,
    "rid": 368380,
    "title": "בדקות הקרובות צפויות להתקבל התרעות באזורך"
  },
  {
    "data": "הגבעה הצהובה",
    "date": "05.03.2026",
    "time": "16:44:04",
    "alertDate": "2026-03-05T16:44:00",
    "category": 13,
    "category_desc": "ירי רקטות וטילים -  האירוע הסתיים",
    "matrix_id": 10,
    "rid": 366234,
    "title": "ירי רקטות וטילים -  האירוע הסתיים"
  },
  {
    "data": "הגבעה הצהובה",
    "date": "05.03.2026",
    "time": "16:24:47",
    "alertDate": "2026-03-05T16:25:00",
    "category": 14,
    "category_desc": "בדקות הקרובות צפויות להתקבל התרעות באזורך",
    "matrix_id": 10,
    "rid": 365284,
    "title": "בדקות הקרובות צפויות להתקבל התרעות באזורך"
  },
  {
    "data": "הגבעה הצהובה",
    "date": "05.03.2026",
    "time": "14:05:02",
    "alertDate": "2026-03-05T14:05:00",
    "category": 13,
    "category_desc": "ירי רקטות וטילים -  האירוע הסתיים",
    "matrix_id": 10,
    "rid": 364622,
    "title": "ירי רקטות וטילים -  האירוע הסתיים"
  },
  {
    "data": "הגבעה הצהובה",
    "date": "05.03.2026",
    "time": "13:54:41",
    "alertDate": "2026-03-05T13:55:00",
    "category": 1,
    "category_desc": "ירי רקטות וטילים",
    "matrix_id": 1,
    "rid": 364361,
    "title": "ירי רקטות וטילים"
  },
  {
    "data": "הגבעה הצהובה",
    "date": "05.03.2026",
    "time": "13:42:07",
    "alertDate": "2026-03-05T13:42:00",
    "category": 14,
    "category_desc": "בדקות הקרובות צפויות להתקבל התרעות באזורך",
    "matrix_id": 10,
    "rid": 363487,
    "title": "בדקות הקרובות צפויות להתקבל התרעות באזורך"
  },
  {
    "data": "הגבעה הצהובה",
    "date": "05.03.2026",
    "time": "10:41:17",
    "alertDate": "2026-03-05T10:41:00",
    "category": 13,
    "category_desc": "ירי רקטות וטילים -  האירוע הסתיים",
    "matrix_id": 10,
    "rid": 362992,
    "title": "ירי רקטות וטילים -  האירוע הסתיים"
  },
  {
    "data": "הגבעה הצהובה",
    "date": "05.03.2026",
    "time": "10:25:40",
    "alertDate": "2026-03-05T10:26:00",
    "category": 14,
    "category_desc": "בדקות הקרובות צפויות להתקבל התרעות באזורך",
    "matrix_id": 10,
    "rid": 362091,
    "title": "בדקות הקרובות צפויות להתקבל התרעות באזורך"
  },
  {
    "data": "הגבעה הצהובה",
    "date": "05.03.2026",
    "time": "04:12:07",
    "alertDate": "2026-03-05T04:12:00",
    "category": 13,
    "category_desc": "ירי רקטות וטילים -  האירוע הסתיים",
    "matrix_id": 10,
    "rid": 361276,
    "title": "ירי רקטות וטילים -  האירוע הסתיים"
  },
  {
    "data": "הגבעה הצהובה",
    "date": "05.03.2026",
    "time": "04:01:20",
    "alertDate": "2026-03-05T04:01:00",
    "category": 1,
    "category_desc": "ירי רקטות וטילים",
    "matrix_id": 1,
    "rid": 360797,
    "title": "ירי רקטות וטילים"
  },
  {
    "data": "הגבעה הצהובה",
    "date": "05.03.2026",
    "time": "03:55:16",
    "alertDate": "2026-03-05T03:55:00",
    "category": 14,
    "category_desc": "בדקות הקרובות צפויות להתקבל התרעות באזורך",
    "matrix_id": 10,
    "rid": 360275,
    "title": "בדקות הקרובות צפויות להתקבל התרעות באזורך"
  },
  {
    "data": "הגבעה הצהובה",
    "date": "04.03.2026",
    "time": "19:14:04",
    "alertDate": "2026-03-04T19:14:00",
    "category": 13,
    "category_desc": "ירי רקטות וטילים -  האירוע הסתיים",
    "matrix_id": 10,
    "rid": 359197,
    "title": "ירי רקטות וטילים -  האירוע הסתיים"
  },
  {
    "data": "הגבעה הצהובה",
    "date": "04.03.2026",
    "time": "18:54:03",
    "alertDate": "2026-03-04T18:54:00",
    "category": 14,
    "category_desc": "בדקות הקרובות צפויות להתקבל התרעות באזורך",
    "matrix_id": 10,
    "rid": 358492,
    "title": "בדקות הקרובות צפויות להתקבל התרעות באזורך"
  },
  {
    "data": "הגבעה הצהובה",
    "date": "04.03.2026",
    "time": "16:26:14",
    "alertDate": "2026-03-04T16:26:00",
    "category": 13,
    "category_desc": "ירי רקטות וטילים -  האירוע הסתיים",
    "matrix_id": 10,
    "rid": 358060,
    "title": "ירי רקטות וטילים -  האירוע הסתיים"
  },
  {
    "data": "הגבעה הצהובה",
    "date": "04.03.2026",
    "time": "16:12:59",
    "alertDate": "2026-03-04T16:13:00",
    "category": 1,
    "category_desc": "ירי רקטות וטילים",
    "matrix_id": 1,
    "rid": 356944,
    "title": "ירי רקטות וטילים"
  },
  {
    "data": "הגבעה הצהובה",
    "date": "04.03.2026",
    "time": "16:07:11",
    "alertDate": "2026-03-04T16:07:00",
    "category": 14,
    "category_desc": "בדקות הקרובות צפויות להתקבל התרעות באזורך",
    "matrix_id": 10,
    "rid": 356334,
    "title": "בדקות הקרובות צפויות להתקבל התרעות באזורך"
  },
  {
    "data": "הגבעה הצהובה",
    "date": "04.03.2026",
    "time": "14:49:56",
    "alertDate": "2026-03-04T14:50:00",
    "category": 13,
    "category_desc": "ירי רקטות וטילים -  האירוע הסתיים",
    "matrix_id": 10,
    "rid": 354890,
    "title": "ירי רקטות וטילים -  האירוע הסתיים"
  },
  {
    "data": "הגבעה הצהובה",
    "date": "04.03.2026",
    "time": "14:30:12",
    "alertDate": "2026-03-04T14:30:00",
    "category": 14,
    "category_desc": "בדקות הקרובות צפויות להתקבל התרעות באזורך",
    "matrix_id": 10,
    "rid": 353881,
    "title": "בדקות הקרובות צפויות להתקבל התרעות באזורך"
  },
  {
    "data": "הגבעה הצהובה",
    "date": "04.03.2026",
    "time": "14:20:39",
    "alertDate": "2026-03-04T14:21:00",
    "category": 13,
    "category_desc": "ירי רקטות וטילים -  האירוע הסתיים",
    "matrix_id": 10,
    "rid": 352915,
    "title": "ירי רקטות וטילים -  האירוע הסתיים"
  },
  {
    "data": "הגבעה הצהובה",
    "date": "04.03.2026",
    "time": "14:07:37",
    "alertDate": "2026-03-04T14:08:00",
    "category": 1,
    "category_desc": "ירי רקטות וטילים",
    "matrix_id": 1,
    "rid": 352666,
    "title": "ירי רקטות וטילים"
  },
  {
    "data": "הגבעה הצהובה",
    "date": "04.03.2026",
    "time": "14:02:38",
    "alertDate": "2026-03-04T14:03:00",
    "category": 14,
    "category_desc": "בדקות הקרובות צפויות להתקבל התרעות באזורך",
    "matrix_id": 10,
    "rid": 351962,
    "title": "בדקות הקרובות צפויות להתקבל התרעות באזורך"
  },
  {
    "data": "הגבעה הצהובה",
    "date": "04.03.2026",
    "time": "13:56:02",
    "alertDate": "2026-03-04T13:56:00",
    "category": 13,
    "category_desc": "ירי רקטות וטילים -  האירוע הסתיים",
    "matrix_id": 10,
    "rid": 351234,
    "title": "ירי רקטות וטילים -  האירוע הסתיים"
  },
  {
    "data": "הגבעה הצהובה",
    "date": "04.03.2026",
    "time": "13:47:40",
    "alertDate": "2026-03-04T13:48:00",
    "category": 14,
    "category_desc": "בדקות הקרובות צפויות להתקבל התרעות באזורך",
    "matrix_id": 10,
    "rid": 350513,
    "title": "בדקות הקרובות צפויות להתקבל התרעות באזורך"
  },
  {
    "data": "הגבעה הצהובה",
    "date": "04.03.2026",
    "time": "06:10:06",
    "alertDate": "2026-03-04T06:10:00",
    "category": 13,
    "category_desc": "ירי רקטות וטילים -  האירוע הסתיים",
    "matrix_id": 10,
    "rid": 350036,
    "title": "ירי רקטות וטילים -  האירוע הסתיים"
  },
  {
    "data": "הגבעה הצהובה",
    "date": "04.03.2026",
    "time": "05:58:24",
    "alertDate": "2026-03-04T05:58:00",
    "category": 1,
    "category_desc": "ירי רקטות וטילים",
    "matrix_id": 1,
    "rid": 348875,
    "title": "ירי רקטות וטילים"
  },
  {
    "data": "הגבעה הצהובה",
    "date": "04.03.2026",
    "time": "05:52:26",
    "alertDate": "2026-03-04T05:52:00",
    "category": 14,
    "category_desc": "בדקות הקרובות צפויות להתקבל התרעות באזורך",
    "matrix_id": 10,
    "rid": 347948,
    "title": "בדקות הקרובות צפויות להתקבל התרעות באזורך"
  },
  {
    "data": "הגבעה הצהובה",
    "date": "03.03.2026",
    "time": "23:28:08",
    "alertDate": "2026-03-03T23:28:00",
    "category": 13,
    "category_desc": "ירי רקטות וטילים -  האירוע הסתיים",
    "matrix_id": 10,
    "rid": 344064,
    "title": "ירי רקטות וטילים -  האירוע הסתיים"
  },
  {
    "data": "הגבעה הצהובה",
    "date": "03.03.2026",
    "time": "23:08:36",
    "alertDate": "2026-03-03T23:09:00",
    "category": 14,
    "category_desc": "בדקות הקרובות צפויות להתקבל התרעות באזורך",
    "matrix_id": 10,
    "rid": 343200,
    "title": "בדקות הקרובות צפויות להתקבל התרעות באזורך"
  },
  {
    "data": "הגבעה הצהובה",
    "date": "03.03.2026",
    "time": "23:00:44",
    "alertDate": "2026-03-03T23:01:00",
    "category": 13,
    "category_desc": "ירי רקטות וטילים -  האירוע הסתיים",
    "matrix_id": 10,
    "rid": 342518,
    "title": "ירי רקטות וטילים -  האירוע הסתיים"
  },
  {
    "data": "הגבעה הצהובה",
    "date": "03.03.2026",
    "time": "22:42:09",
    "alertDate": "2026-03-03T22:42:00",
    "category": 14,
    "category_desc": "בדקות הקרובות צפויות להתקבל התרעות באזורך",
    "matrix_id": 10,
    "rid": 341499,
    "title": "בדקות הקרובות צפויות להתקבל התרעות באזורך"
  },
  {
    "data": "הגבעה הצהובה",
    "date": "03.03.2026",
    "time": "15:11:57",
    "alertDate": "2026-03-03T15:12:00",
    "category": 13,
    "category_desc": "ירי רקטות וטילים -  האירוע הסתיים",
    "matrix_id": 10,
    "rid": 340209,
    "title": "ירי רקטות וטילים -  האירוע הסתיים"
  },
  {
    "data": "הגבעה הצהובה",
    "date": "03.03.2026",
    "time": "14:45:07",
    "alertDate": "2026-03-03T14:45:00",
    "category": 14,
    "category_desc": "בדקות הקרובות צפויות להתקבל התרעות באזורך",
    "matrix_id": 10,
    "rid": 338655,
    "title": "בדקות הקרובות צפויות להתקבל התרעות באזורך"
  },
  {
    "data": "הגבעה הצהובה",
    "date": "03.03.2026",
    "time": "12:54:07",
    "alertDate": "2026-03-03T12:54:00",
    "category": 13,
    "category_desc": "ירי רקטות וטילים -  האירוע הסתיים",
    "matrix_id": 10,
    "rid": 337322,
    "title": "ירי רקטות וטילים -  האירוע הסתיים"
  },
  {
    "data": "הגבעה הצהובה",
    "date": "03.03.2026",
    "time": "12:38:43",
    "alertDate": "2026-03-03T12:39:00",
    "category": 1,
    "category_desc": "ירי רקטות וטילים",
    "matrix_id": 1,
    "rid": 336727,
    "title": "ירי רקטות וטילים"
  },
  {
    "data": "הגבעה הצהובה",
    "date": "03.03.2026",
    "time": "12:22:02",
    "alertDate": "2026-03-03T12:22:00",
    "category": 14,
    "category_desc": "בדקות הקרובות צפויות להתקבל התרעות באזורך",
    "matrix_id": 10,
    "rid": 336003,
    "title": "בדקות הקרובות צפויות להתקבל התרעות באזורך"
  },
  {
    "data": "הגבעה הצהובה",
    "date": "03.03.2026",
    "time": "11:26:00",
    "alertDate": "2026-03-03T11:26:00",
    "category": 13,
    "category_desc": "ירי רקטות וטילים -  האירוע הסתיים",
    "matrix_id": 10,
    "rid": 335397,
    "title": "ירי רקטות וטילים -  האירוע הסתיים"
  },
  {
    "data": "הגבעה הצהובה",
    "date": "03.03.2026",
    "time": "11:07:29",
    "alertDate": "2026-03-03T11:07:00",
    "category": 14,
    "category_desc": "בדקות הקרובות צפויות להתקבל התרעות באזורך",
    "matrix_id": 10,
    "rid": 334601,
    "title": "בדקות הקרובות צפויות להתקבל התרעות באזורך"
  },
  {
    "data": "הגבעה הצהובה",
    "date": "03.03.2026",
    "time": "00:59:08",
    "alertDate": "2026-03-03T00:59:00",
    "category": 13,
    "category_desc": "ירי רקטות וטילים -  האירוע הסתיים",
    "matrix_id": 10,
    "rid": 332724,
    "title": "ירי רקטות וטילים -  האירוע הסתיים"
  },
  {
    "data": "הגבעה הצהובה",
    "date": "03.03.2026",
    "time": "00:38:33",
    "alertDate": "2026-03-03T00:39:00",
    "category": 14,
    "category_desc": "בדקות הקרובות צפויות להתקבל התרעות באזורך",
    "matrix_id": 10,
    "rid": 330576,
    "title": "בדקות הקרובות צפויות להתקבל התרעות באזורך"
  },
  {
    "data": "הגבעה הצהובה",
    "date": "02.03.2026",
    "time": "17:48:08",
    "alertDate": "2026-03-02T17:48:00",
    "category": 13,
    "category_desc": "ירי רקטות וטילים -  האירוע הסתיים",
    "matrix_id": 10,
    "rid": 328524,
    "title": "ירי רקטות וטילים -  האירוע הסתיים"
  },
  {
    "data": "הגבעה הצהובה",
    "date": "02.03.2026",
    "time": "17:26:09",
    "alertDate": "2026-03-02T17:26:00",
    "category": 14,
    "category_desc": "בדקות הקרובות צפויות להתקבל התרעות באזורך",
    "matrix_id": 10,
    "rid": 327696,
    "title": "בדקות הקרובות צפויות להתקבל התרעות באזורך"
  },
  {
    "data": "הגבעה הצהובה",
    "date": "02.03.2026",
    "time": "13:03:33",
    "alertDate": "2026-03-02T13:04:00",
    "category": 13,
    "category_desc": "ירי רקטות וטילים -  האירוע הסתיים",
    "matrix_id": 10,
    "rid": 326265,
    "title": "ירי רקטות וטילים -  האירוע הסתיים"
  },
  {
    "data": "הגבעה הצהובה",
    "date": "02.03.2026",
    "time": "12:31:22",
    "alertDate": "2026-03-02T12:31:00",
    "category": 14,
    "category_desc": "בדקות הקרובות צפויות להתקבל התרעות באזורך",
    "matrix_id": 10,
    "rid": 323772,
    "title": "בדקות הקרובות צפויות להתקבל התרעות באזורך"
  },
  {
    "data": "הגבעה הצהובה",
    "date": "02.03.2026",
    "time": "12:24:18",
    "alertDate": "2026-03-02T12:24:00",
    "category": 13,
    "category_desc": "ירי רקטות וטילים -  האירוע הסתיים",
    "matrix_id": 10,
    "rid": 323110,
    "title": "ירי רקטות וטילים -  האירוע הסתיים"
  },
  {
    "data": "הגבעה הצהובה",
    "date": "02.03.2026",
    "time": "12:02:10",
    "alertDate": "2026-03-02T12:02:00",
    "category": 14,
    "category_desc": "בדקות הקרובות צפויות להתקבל התרעות באזורך",
    "matrix_id": 10,
    "rid": 322439,
    "title": "בדקות הקרובות צפויות להתקבל התרעות באזורך"
  },
  {
    "data": "הגבעה הצהובה",
    "date": "02.03.2026",
    "time": "08:04:52",
    "alertDate": "2026-03-02T08:05:00",
    "category": 13,
    "category_desc": "ירי רקטות וטילים -  האירוע הסתיים",
    "matrix_id": 10,
    "rid": 321531,
    "title": "ירי רקטות וטילים -  האירוע הסתיים"
  },
  {
    "data": "הגבעה הצהובה",
    "date": "02.03.2026",
    "time": "07:37:28",
    "alertDate": "2026-03-02T07:37:00",
    "category": 1,
    "category_desc": "ירי רקטות וטילים",
    "matrix_id": 1,
    "rid": 320564,
    "title": "ירי רקטות וטילים"
  },
  {
    "data": "הגבעה הצהובה",
    "date": "02.03.2026",
    "time": "07:30:23",
    "alertDate": "2026-03-02T07:30:00",
    "category": 14,
    "category_desc": "בדקות הקרובות צפויות להתקבל התרעות באזורך",
    "matrix_id": 10,
    "rid": 320011,
    "title": "בדקות הקרובות צפויות להתקבל התרעות באזורך"
  },
  {
    "data": "הגבעה הצהובה",
    "date": "02.03.2026",
    "time": "07:23:45",
    "alertDate": "2026-03-02T07:24:00",
    "category": 13,
    "category_desc": "ירי רקטות וטילים -  האירוע הסתיים",
    "matrix_id": 10,
    "rid": 319072,
    "title": "ירי רקטות וטילים -  האירוע הסתיים"
  },
  {
    "data": "הגבעה הצהובה",
    "date": "02.03.2026",
    "time": "07:06:50",
    "alertDate": "2026-03-02T07:07:00",
    "category": 1,
    "category_desc": "ירי רקטות וטילים",
    "matrix_id": 1,
    "rid": 318381,
    "title": "ירי רקטות וטילים"
  },
  {
    "data": "הגבעה הצהובה",
    "date": "02.03.2026",
    "time": "07:02:00",
    "alertDate": "2026-03-02T07:02:00",
    "category": 14,
    "category_desc": "בדקות הקרובות צפויות להתקבל התרעות באזורך",
    "matrix_id": 10,
    "rid": 317794,
    "title": "בדקות הקרובות צפויות להתקבל התרעות באזורך"
  },
  {
    "data": "הגבעה הצהובה",
    "date": "01.03.2026",
    "time": "22:47:55",
    "alertDate": "2026-03-01T22:48:00",
    "category": 13,
    "category_desc": "ירי רקטות וטילים -  האירוע הסתיים",
    "matrix_id": 10,
    "rid": 316384,
    "title": "ירי רקטות וטילים -  האירוע הסתיים"
  },
  {
    "data": "הגבעה הצהובה",
    "date": "01.03.2026",
    "time": "22:28:02",
    "alertDate": "2026-03-01T22:28:00",
    "category": 14,
    "category_desc": "בדקות הקרובות צפויות להתקבל התרעות באזורך",
    "matrix_id": 10,
    "rid": 315529,
    "title": "בדקות הקרובות צפויות להתקבל התרעות באזורך"
  },
  {
    "data": "הגבעה הצהובה",
    "date": "01.03.2026",
    "time": "21:37:50",
    "alertDate": "2026-03-01T21:38:00",
    "category": 13,
    "category_desc": "ניתן לצאת מהמרחב המוגן אך יש להישאר בקרבתו",
    "matrix_id": 10,
    "rid": 314637,
    "title": "ניתן לצאת מהמרחב המוגן אך יש להישאר בקרבתו"
  },
  {
    "data": "הגבעה הצהובה",
    "date": "01.03.2026",
    "time": "21:11:02",
    "alertDate": "2026-03-01T21:11:00",
    "category": 1,
    "category_desc": "ירי רקטות וטילים",
    "matrix_id": 1,
    "rid": 313451,
    "title": "ירי רקטות וטילים"
  },
  {
    "data": "הגבעה הצהובה",
    "date": "01.03.2026",
    "time": "21:05:30",
    "alertDate": "2026-03-01T21:06:00",
    "category": 14,
    "category_desc": "בדקות הקרובות צפויות להתקבל התרעות באזורך",
    "matrix_id": 10,
    "rid": 312148,
    "title": "בדקות הקרובות צפויות להתקבל התרעות באזורך"
  },
  {
    "data": "הגבעה הצהובה",
    "date": "01.03.2026",
    "time": "14:03:35",
    "alertDate": "2026-03-01T14:04:00",
    "category": 13,
    "category_desc": "ניתן לצאת מהמרחב המוגן אך יש להישאר בקרבתו",
    "matrix_id": 10,
    "rid": 308752,
    "title": "ניתן לצאת מהמרחב המוגן אך יש להישאר בקרבתו"
  },
  {
    "data": "הגבעה הצהובה",
    "date": "01.03.2026",
    "time": "13:41:41",
    "alertDate": "2026-03-01T13:42:00",
    "category": 1,
    "category_desc": "ירי רקטות וטילים",
    "matrix_id": 1,
    "rid": 307043,
    "title": "ירי רקטות וטילים"
  },
  {
    "data": "הגבעה הצהובה",
    "date": "01.03.2026",
    "time": "13:21:56",
    "alertDate": "2026-03-01T13:22:00",
    "category": 14,
    "category_desc": "בדקות הקרובות צפויות להתקבל התרעות באזורך",
    "matrix_id": 10,
    "rid": 304736,
    "title": "בדקות הקרובות צפויות להתקבל התרעות באזורך"
  },
  {
    "data": "הגבעה הצהובה",
    "date": "01.03.2026",
    "time": "13:01:32",
    "alertDate": "2026-03-01T13:02:00",
    "category": 13,
    "category_desc": "ניתן לצאת מהמרחב המוגן אך יש להישאר בקרבתו",
    "matrix_id": 10,
    "rid": 304070,
    "title": "ניתן לצאת מהמרחב המוגן אך יש להישאר בקרבתו"
  },
  {
    "data": "הגבעה הצהובה",
    "date": "01.03.2026",
    "time": "12:38:23",
    "alertDate": "2026-03-01T12:38:00",
    "category": 14,
    "category_desc": "בדקות הקרובות צפויות להתקבל התרעות באזורך",
    "matrix_id": 10,
    "rid": 303165,
    "title": "בדקות הקרובות צפויות להתקבל התרעות באזורך"
  },
  {
    "data": "הגבעה הצהובה",
    "date": "01.03.2026",
    "time": "10:37:31",
    "alertDate": "2026-03-01T10:38:00",
    "category": 13,
    "category_desc": "ניתן לצאת מהמרחב המוגן אך יש להישאר בקרבתו",
    "matrix_id": 10,
    "rid": 302247,
    "title": "ניתן לצאת מהמרחב המוגן אך יש להישאר בקרבתו"
  },
  {
    "data": "הגבעה הצהובה",
    "date": "01.03.2026",
    "time": "09:59:27",
    "alertDate": "2026-03-01T09:59:00",
    "category": 14,
    "category_desc": "בדקות הקרובות צפויות להתקבל התרעות באזורך",
    "matrix_id": 10,
    "rid": 298736,
    "title": "בדקות הקרובות צפויות להתקבל התרעות באזורך"
  },
  {
    "data": "הגבעה הצהובה",
    "date": "01.03.2026",
    "time": "09:11:30",
    "alertDate": "2026-03-01T09:12:00",
    "category": 13,
    "category_desc": "ניתן לצאת מהמרחב המוגן אך יש להישאר בקרבתו",
    "matrix_id": 10,
    "rid": 297486,
    "title": "ניתן לצאת מהמרחב המוגן אך יש להישאר בקרבתו"
  },
  {
    "data": "הגבעה הצהובה",
    "date": "01.03.2026",
    "time": "08:59:04",
    "alertDate": "2026-03-01T08:59:00",
    "category": 1,
    "category_desc": "ירי רקטות וטילים",
    "matrix_id": 1,
    "rid": 296744,
    "title": "ירי רקטות וטילים"
  },
  {
    "data": "הגבעה הצהובה",
    "date": "01.03.2026",
    "time": "08:49:15",
    "alertDate": "2026-03-01T08:49:00",
    "category": 14,
    "category_desc": "בדקות הקרובות צפויות להתקבל התרעות באזורך",
    "matrix_id": 10,
    "rid": 295285,
    "title": "בדקות הקרובות צפויות להתקבל התרעות באזורך"
  },
  {
    "data": "הגבעה הצהובה",
    "date": "01.03.2026",
    "time": "07:20:32",
    "alertDate": "2026-03-01T07:21:00",
    "category": 13,
    "category_desc": "ניתן לצאת מהמרחב המוגן אך יש להישאר בקרבתו",
    "matrix_id": 10,
    "rid": 294742,
    "title": "ניתן לצאת מהמרחב המוגן אך יש להישאר בקרבתו"
  },
  {
    "data": "הגבעה הצהובה",
    "date": "01.03.2026",
    "time": "06:08:51",
    "alertDate": "2026-03-01T06:09:00",
    "category": 14,
    "category_desc": "בדקות הקרובות צפויות להתקבל התרעות באזורך",
    "matrix_id": 10,
    "rid": 291282,
    "title": "בדקות הקרובות צפויות להתקבל התרעות באזורך"
  },
  {
    "data": "הגבעה הצהובה",
    "date": "01.03.2026",
    "time": "02:06:10",
    "alertDate": "2026-03-01T02:06:00",
    "category": 13,
    "category_desc": "ניתן לצאת מהמרחב המוגן אך יש להישאר בקרבתו",
    "matrix_id": 10,
    "rid": 271224,
    "title": "ניתן לצאת מהמרחב המוגן אך יש להישאר בקרבתו"
  },
  {
    "data": "הגבעה הצהובה",
    "date": "01.03.2026",
    "time": "01:43:07",
    "alertDate": "2026-03-01T01:43:00",
    "category": 1,
    "category_desc": "ירי רקטות וטילים",
    "matrix_id": 1,
    "rid": 270429,
    "title": "ירי רקטות וטילים"
  },
  {
    "data": "הגבעה הצהובה",
    "date": "01.03.2026",
    "time": "01:40:02",
    "alertDate": "2026-03-01T01:40:00",
    "category": 14,
    "category_desc": "בדקות הקרובות צפויות להתקבל התרעות באזורך",
    "matrix_id": 10,
    "rid": 269928,
    "title": "בדקות הקרובות צפויות להתקבל התרעות באזורך"
  },
  {
    "data": "הגבעה הצהובה",
    "date": "28.02.2026",
    "time": "23:02:09",
    "alertDate": "2026-02-28T23:02:00",
    "category": 13,
    "category_desc": "ניתן לצאת מהמרחב המוגן אך יש להישאר בקרבתו",
    "matrix_id": 10,
    "rid": 268279,
    "title": "ניתן לצאת מהמרחב המוגן אך יש להישאר בקרבתו"
  },
  {
    "data": "הגבעה הצהובה",
    "date": "28.02.2026",
    "time": "22:30:16",
    "alertDate": "2026-02-28T22:30:00",
    "category": 14,
    "category_desc": "בדקות הקרובות צפויות להתקבל התרעות באזורך",
    "matrix_id": 10,
    "rid": 265947,
    "title": "בדקות הקרובות צפויות להתקבל התרעות באזורך"
  },
  {
    "data": "הגבעה הצהובה",
    "date": "28.02.2026",
    "time": "19:35:40",
    "alertDate": "2026-02-28T19:36:00",
    "category": 13,
    "category_desc": "ניתן לצאת מהמרחב המוגן אך יש להישאר בקרבתו",
    "matrix_id": 10,
    "rid": 265250,
    "title": "ניתן לצאת מהמרחב המוגן אך יש להישאר בקרבתו"
  },
  {
    "data": "הגבעה הצהובה",
    "date": "28.02.2026",
    "time": "19:18:16",
    "alertDate": "2026-02-28T19:18:00",
    "category": 14,
    "category_desc": "בדקות הקרובות צפויות להתקבל התרעות באזורך",
    "matrix_id": 10,
    "rid": 264436,
    "title": "בדקות הקרובות צפויות להתקבל התרעות באזורך"
  },
  {
    "data": "הגבעה הצהובה",
    "date": "28.02.2026",
    "time": "19:05:00",
    "alertDate": "2026-02-28T19:05:00",
    "category": 13,
    "category_desc": "ניתן לצאת מהמרחב המוגן אך יש להישאר בקרבתו",
    "matrix_id": 10,
    "rid": 263769,
    "title": "ניתן לצאת מהמרחב המוגן אך יש להישאר בקרבתו"
  },
  {
    "data": "הגבעה הצהובה",
    "date": "28.02.2026",
    "time": "19:01:31",
    "alertDate": "2026-02-28T19:02:00",
    "category": 13,
    "category_desc": "ניתן לצאת מהמרחב המוגן אך יש להישאר בקרבתו",
    "matrix_id": 10,
    "rid": 263102,
    "title": "ניתן לצאת מהמרחב המוגן אך יש להישאר בקרבתו"
  },
  {
    "data": "הגבעה הצהובה",
    "date": "28.02.2026",
    "time": "17:29:38",
    "alertDate": "2026-02-28T17:30:00",
    "category": 14,
    "category_desc": "בדקות הקרובות צפויות להתקבל התרעות באזורך",
    "matrix_id": 10,
    "rid": 256999,
    "title": "בדקות הקרובות צפויות להתקבל התרעות באזורך"
  },
  {
    "data": "הגבעה הצהובה",
    "date": "28.02.2026",
    "time": "17:24:20",
    "alertDate": "2026-02-28T17:24:00",
    "category": 13,
    "category_desc": "ניתן לצאת מהמרחב המוגן אך יש להישאר בקרבתו",
    "matrix_id": 10,
    "rid": 256339,
    "title": "ניתן לצאת מהמרחב המוגן אך יש להישאר בקרבתו"
  },
  {
    "data": "הגבעה הצהובה",
    "date": "28.02.2026",
    "time": "16:48:20",
    "alertDate": "2026-02-28T16:48:00",
    "category": 14,
    "category_desc": "בדקות הקרובות צפויות להתקבל התרעות באזורך",
    "matrix_id": 10,
    "rid": 255166,
    "title": "בדקות הקרובות צפויות להתקבל התרעות באזורך"
  },
  {
    "data": "הגבעה הצהובה",
    "date": "28.02.2026",
    "time": "16:27:45",
    "alertDate": "2026-02-28T16:28:00",
    "category": 14,
    "category_desc": "בדקות הקרובות צפויות להתקבל התרעות באזורך",
    "matrix_id": 10,
    "rid": 254147,
    "title": "בדקות הקרובות צפויות להתקבל התרעות באזורך"
  },
  {
    "data": "הגבעה הצהובה",
    "date": "28.02.2026",
    "time": "16:22:29",
    "alertDate": "2026-02-28T16:22:00",
    "category": 13,
    "category_desc": "ניתן לצאת מהמרחב המוגן אך יש להישאר בקרבתו",
    "matrix_id": 10,
    "rid": 253506,
    "title": "ניתן לצאת מהמרחב המוגן אך יש להישאר בקרבתו"
  },
  {
    "data": "הגבעה הצהובה",
    "date": "28.02.2026",
    "time": "15:44:09",
    "alertDate": "2026-02-28T15:44:00",
    "category": 14,
    "category_desc": "בדקות הקרובות צפויות להתקבל התרעות באזורך",
    "matrix_id": 10,
    "rid": 251323,
    "title": "בדקות הקרובות צפויות להתקבל התרעות באזורך"
  },
  {
    "data": "הגבעה הצהובה",
    "date": "28.02.2026",
    "time": "14:55:14",
    "alertDate": "2026-02-28T14:55:00",
    "category": 13,
    "category_desc": "ניתן לצאת מהמרחב המוגן אך יש להישאר בקרבתו",
    "matrix_id": 10,
    "rid": 249528,
    "title": "ניתן לצאת מהמרחב המוגן אך יש להישאר בקרבתו"
  },
  {
    "data": "הגבעה הצהובה",
    "date": "28.02.2026",
    "time": "14:43:19",
    "alertDate": "2026-02-28T14:43:00",
    "category": 1,
    "category_desc": "ירי רקטות וטילים",
    "matrix_id": 1,
    "rid": 249220,
    "title": "ירי רקטות וטילים"
  },
  {
    "data": "הגבעה הצהובה",
    "date": "28.02.2026",
    "time": "14:36:27",
    "alertDate": "2026-02-28T14:36:00",
    "category": 14,
    "category_desc": "בדקות הקרובות צפויות להתקבל התרעות באזורך",
    "matrix_id": 10,
    "rid": 248354,
    "title": "בדקות הקרובות צפויות להתקבל התרעות באזורך"
  },
  {
    "data": "הגבעה הצהובה",
    "date": "28.02.2026",
    "time": "13:29:34",
    "alertDate": "2026-02-28T13:30:00",
    "category": 13,
    "category_desc": "ניתן לצאת מהמרחב המוגן אך יש להישאר בקרבתו",
    "matrix_id": 10,
    "rid": 246922,
    "title": "ניתן לצאת מהמרחב המוגן אך יש להישאר בקרבתו"
  },
  {
    "data": "הגבעה הצהובה",
    "date": "28.02.2026",
    "time": "13:03:47",
    "alertDate": "2026-02-28T13:04:00",
    "category": 14,
    "category_desc": "בדקות הקרובות צפויות להתקבל התרעות באזורך",
    "matrix_id": 10,
    "rid": 245795,
    "title": "בדקות הקרובות צפויות להתקבל התרעות באזורך"
  },
  {
    "data": "הגבעה הצהובה",
    "date": "28.02.2026",
    "time": "12:41:58",
    "alertDate": "2026-02-28T12:42:00",
    "category": 13,
    "category_desc": "ניתן לצאת מהמרחב המוגן אך יש להישאר בקרבתו",
    "matrix_id": 10,
    "rid": 244748,
    "title": "ניתן לצאת מהמרחב המוגן אך יש להישאר בקרבתו"
  },
  {
    "data": "הגבעה הצהובה",
    "date": "28.02.2026",
    "time": "12:30:43",
    "alertDate": "2026-02-28T12:31:00",
    "category": 1,
    "category_desc": "ירי רקטות וטילים",
    "matrix_id": 1,
    "rid": 244470,
    "title": "ירי רקטות וטילים"
  },
  {
    "data": "הגבעה הצהובה",
    "date": "28.02.2026",
    "time": "12:24:07",
    "alertDate": "2026-02-28T12:24:00",
    "category": 14,
    "category_desc": "בדקות הקרובות צפויות להתקבל התרעות באזורך",
    "matrix_id": 10,
    "rid": 243740,
    "title": "בדקות הקרובות צפויות להתקבל התרעות באזורך"
  },
  {
    "data": "הגבעה הצהובה",
    "date": "28.02.2026",
    "time": "11:53:09",
    "alertDate": "2026-02-28T11:53:00",
    "category": 1,
    "category_desc": "ירי רקטות וטילים",
    "matrix_id": 1,
    "rid": 243205,
    "title": "ירי רקטות וטילים"
  },
  {
    "data": "הגבעה הצהובה",
    "date": "28.02.2026",
    "time": "11:29:43",
    "alertDate": "2026-02-28T11:30:00",
    "category": 1,
    "category_desc": "ירי רקטות וטילים",
    "matrix_id": 1,
    "rid": 241955,
    "title": "ירי רקטות וטילים"
  },
  {
    "data": "הגבעה הצהובה",
    "date": "28.02.2026",
    "time": "11:20:36",
    "alertDate": "2026-02-28T11:21:00",
    "category": 1,
    "category_desc": "ירי רקטות וטילים",
    "matrix_id": 1,
    "rid": 240611,
    "title": "ירי רקטות וטילים"
  },
  {
    "data": "הגבעה הצהובה",
    "date": "28.02.2026",
    "time": "11:15:29",
    "alertDate": "2026-02-28T11:15:00",
    "category": 1,
    "category_desc": "ירי רקטות וטילים",
    "matrix_id": 1,
    "rid": 240298,
    "title": "ירי רקטות וטילים"
  },
  {
    "data": "הגבעה הצהובה",
    "date": "28.02.2026",
    "time": "10:36:48",
    "alertDate": "2026-02-28T10:37:00",
    "category": 1,
    "category_desc": "ירי רקטות וטילים",
    "matrix_id": 1,
    "rid": 237881,
    "title": "ירי רקטות וטילים"
  }
]